jj_clean/__init__.py
jj_clean-0.0.1.dist-info/METADATA
jj_clean-0.0.1.dist-info/WHEEL
jj_clean-0.0.1.dist-info/entry_points.txt
jj_clean-0.0.1.dist-info/RECORD
