Metadata-Version: 2.4
Name: jj-clean
Version: 0.0.1
Summary: Add your description here
Author-email: CD Clark III <clifton.clark@gmail.com>
Requires-Python: >=3.12
